{
    "FlowerDance_Accept_Spouse": "*唉* ……我是花女王的時代已經結束了……所以對我來說這是一次苦樂參半的舞蹈。$s#$b#但是，是的……",
    "dating_Haley": "我一直在等你約我呢。$l",
    "eventSeen_12_memory_twoweeks": "我爸媽又寄來了一張明信片……估計他們在坐郵輪經過寶石海岸。#$e#他們說我和艾米麗隨時都可以去，但說實話……誰想跟父母一起度假呢？",
    "AcceptBirthdayGift_Liked": "哇，你給我準備生日禮物了？我很喜歡！$h",
    "AcceptGift_(O)88": "這個是椰子吧？我超喜歡的！$h#$b#讓我想起了在海灘上玩的時候，天氣溫暖，陽光明媚，拿著這個感覺身臨其境……",
    "GreenRain": "我好像還沒來過這裡，還挺舒服的！$h#$e#啊，我不是很擔心這場雨，肯定會停的。",
    "eventSeen_11_memory_oneweek": "前幾天，艾米麗烤了一個東西，她說叫“松鼠麵包”……$u#$e#味道嗎，呃……如果我真有毛茸茸的尾巴，或許會喜歡吧。$h",
    "eventSeen_13_memory_oneweek": "%海莉對你笑了一下。你注意到她戴著曾祖母的手鐲。",
    "dating_Haley_memory_oneyear": "所以你想怎麼樣……要我就這麼一直當你的“女朋友”嗎？$7",
    "married_Emily_memory_oneweek": "艾米麗適應農場生活了嗎？#$e#我跟你說，我之前還在想艾米麗會不會就不結婚了……",
    "eventSeen_14": "拍照真的很開心，但是後來我洗了兩個小時的澡才把頭髮裡的泥巴洗乾淨！$h",
    "AcceptGift_(O)421": "哇，好漂亮啊！我最喜歡這個了。$h",
    "married_Emily": "所以你現在是我的姐夫是吧？想想還挺有趣的。^哎，我們這樣就能算姐妹啦！$h",
    "dating_Haley_memory_oneday": "你今天真的好帥。$l^你今天真的好漂亮。$l",
    "AcceptGift_(O)StardropTea": "送我的？欸……不知道是應該喝了，還是用來洗頭髮……",
    "AcceptBirthdayGift_Negative": "好噁心！我生日你就送我這個？你在搞什麼東西！$a",
    "FlowerDance_Accept": "啊……你是想邀請本小姐跳舞嗎？$13^啊？好呀！我可以跟你跳舞！#$b#嘻嘻……當然可以，我很樂意做你的舞伴。$h^我們玩個痛快吧！$h#$e#唔……你挺自信的，我很欣賞。其他男生太害羞了，都不敢邀請我。^你今天真的好漂亮！$h",
    "cropMatured_421": "我的名字意思是“乾草機器地”，但我更喜歡把它想像成開滿向日葵的草地……",
    "eventSeen_12_memory_oneweek": "哇，好像有人讀過了最新一期的《超級時尚女孩》……沾了泥巴的靴子現在超流行！$h",
    "AcceptBirthdayGift_Loved": "嘶……這是送我的嗎？哇，@，這是我收到的最棒的生日禮物！$h",
    "divorced_Emily": "看來你跟艾米麗合不來啊？唉……也是常有的事。#$e#而且住在小鎮上抬頭不見低頭見的，確實挺尷尬。",
    "FlowerDance_Decline": "額……不。",
    "GreenRain_2": "假如下粉色的雨再叫醒我吧……能下粉色的蛋糕雨那就更好了！",
    "eventSeen_11_memory_twoweeks": "你看昨晚播的那集《淚水》了嗎？嗚嗚……卡爾和埃米居然分手了……$s",
    "winter_9": "唔，你的襯衫是什麼牌子的？#$e#噢。呃，沒什麼。",
    "Introduction": "噢……你就是那個新來的農夫吧？^噢……你就是那個新來的農場姑娘吧？#$e#扇貝？噢……我是海莉。#$e#嗯……要不是你那身衣服，你應該還挺可愛的吧。^嗯……要不是你那身衣服，你應該還挺漂亮的吧。……呃，別介意。$h",
    "Resort_Towel": "要曬成完美的棕褐色皮膚是一門藝術活……#$e#有點像烤棉花糖……你旋轉身體的節奏得剛剛好。$h"
}