{
    "header": {
        "target": "w",
        "formatVersion": 5,
        "hidef": true,
        "compressed": false
    },
    "readers": [
        {
            "type": "Microsoft.Xna.Framework.Content.DictionaryReader`2[[System.String, mscorlib, Version=4.0.0.0, Culture=neutral, PublicKeyToken=b77a5c561934e089],[System.String, mscorlib, Version=4.0.0.0, Culture=neutral, PublicKeyToken=b77a5c561934e089]]",
            "version": 0
        },
        {
            "type": "Microsoft.Xna.Framework.Content.StringReader",
            "version": 0
        }
    ],
    "content": {
        "Introduction": "你好呀！看到有年輕人搬進谷裡真是太高興了。如今這種事可不多見了。",
        "accept_869": "啊……我一直都想抓一條鯰魚，這就是最完美的魚餌！#$b#來吧，我用這個東西與你交換。我不知道這是什麼，但它是在不久前才被沖到海灘上的。#$b#我有種感覺，你會用上它的，小伙子。^我有種感覺，你會用上它的，小姑娘。",
        "FullCrabPond": "（聞聞）啊……這熟悉的味道，你有在養螃蟹對吧？#$b#你跟我真是臭味相投啊，@。哈！$h^你跟我真是臭味相投啊，@。哈！$h#$b#來，這個拿去，我在沙灘上找到的……我一直留著它直到特殊的場合。我可不是每天都能找到一個跟我一樣的螃蟹愛好者！[797]",
        "MovieInvitation": "看電影啊……你人真好，小子。^看電影啊……你人真好，女孩。#$b#我抽完菸斗就過去。",
        "Mon": "你好啊，孩子。^你好啊，女孩。#$b#今天天氣很適合釣魚嘛，是吧？",
        "Mon4": "你在本地水域有什麼收穫嗎？看你的樣子，如果勤加鍛鍊一定會成為出色的釣手哦。",
        "Tue": "真正的釣者必須懂得尊重水……這一點可不要忘了。",
        "Tue6": "我這個老頭子可是個資深漁夫，你知道的。我從小就在各個島嶼之間航行，在到處抓魚的生活中長大的。#$e#漁夫的生活十分艱難，卻有著神奇的魅力。",
        "Wed": "有些魚會隨著季節變化出現或消失，也有些魚只會在下雨或者夜間才會出現。",
        "Thu": "（喃喃自語）……什麼？我其實挺想把我的想法告訴你，但這是漁夫的秘密。",
        "Thu2": "據說這一片水域會出現很稀有的魚……但是只有經驗豐富的高手才有可能戰勝他們。#$e#想要讓稀有的魚上鉤，得要用最好的魚餌才行。",
        "Fri": "如果想讓魚上鉤，可別忘了在鉤子上放魚餌哦。",
        "Sat": "如果本地的垂釣事業能夠更蓬勃一些，也許我會考慮引進新貨。",
        "Sat8": "釣魚釣的怎麼樣啊？#$e#我一有機會就去釣魚，但還有店裡要顧，所以機會並不多啊。",
        "Sun": "如果購買高級釣竿，你就可以在釣魚線上掛上魚餌和釣具。#$b#魚餌可以讓魚兒更快上鉤，釣具則可以讓收線過程更輕鬆。#$e#釣具也有很多種，各有各的優點。這些東西都比較脆弱，所以如果使用了一陣子之後釣具壞掉了也不用太驚訝。",
        "Sun10": "哎呀呀，這不是@船長嘛！$h#$e#要是我能負擔得起，我會給你的魚餌打個折。$s"
    }
}